Metadata-Version: 1.0
Name: hs-dl
Version: 1.1.0
Summary: Simple Horrible Subs Downloader
Home-page: UNKNOWN
Author: samyak
Author-email: UNKNOWN
License: MIT
Project-URL: Documentation, http://hs-dl.readthedocs.io/
Project-URL: Source Code, https://github.com/samyakahuja/hs_dl
Platform: UNKNOWN
